odoo/addons/stock_inventory_virtual_location/README.rst
odoo/addons/stock_inventory_virtual_location/__init__.py
odoo/addons/stock_inventory_virtual_location/__manifest__.py
odoo/addons/stock_inventory_virtual_location/i18n/sl.po
odoo/addons/stock_inventory_virtual_location/i18n/stock_inventory_virtual_location.pot
odoo/addons/stock_inventory_virtual_location/models/__init__.py
odoo/addons/stock_inventory_virtual_location/models/stock_inventory_line.py
odoo/addons/stock_inventory_virtual_location/readme/CONTRIBUTORS.rst
odoo/addons/stock_inventory_virtual_location/readme/DESCRIPTION.rst
odoo/addons/stock_inventory_virtual_location/readme/ROADMAP.rst
odoo/addons/stock_inventory_virtual_location/static/description/icon.png
odoo/addons/stock_inventory_virtual_location/static/description/index.html
odoo/addons/stock_inventory_virtual_location/tests/__init__.py
odoo/addons/stock_inventory_virtual_location/tests/test_stock_inventory_virtual_location.py
odoo/addons/stock_inventory_virtual_location/views/stock_inventory_line_view.xml
odoo/addons/stock_inventory_virtual_location/wizard/__init__.py
odoo/addons/stock_inventory_virtual_location/wizard/stock_change_product_qty.py
odoo/addons/stock_inventory_virtual_location/wizard/stock_product_change_qty.xml
odoo12_addon_stock_inventory_virtual_location-12.0.1.0.0.99.dev6.dist-info/METADATA
odoo12_addon_stock_inventory_virtual_location-12.0.1.0.0.99.dev6.dist-info/WHEEL
odoo12_addon_stock_inventory_virtual_location-12.0.1.0.0.99.dev6.dist-info/top_level.txt
odoo12_addon_stock_inventory_virtual_location-12.0.1.0.0.99.dev6.dist-info/RECORD
